pytest_mock_generator/__init__.py
pytest_mock_generator/py.typed
pytest_mock_generator-1.2.0.dist-info/entry_points.txt
pytest_mock_generator-1.2.0.dist-info/LICENSE
pytest_mock_generator-1.2.0.dist-info/WHEEL
pytest_mock_generator-1.2.0.dist-info/METADATA
pytest_mock_generator-1.2.0.dist-info/RECORD
