Metadata-Version: 2.1
Name: pytest-mock-generator
Version: 1.2.0
Summary: A pytest fixture wrapper for https://pypi.org/project/mock-generator
Home-page: https://github.com/pksol/pytest-mock-generator
License: MIT
Keywords: pytest,mocks,testing,fixtures,tests
Author: Peter Kogan
Author-email: kogan.peter@gmail.com
Requires-Python: >=3.7,<4.0
Classifier: Development Status :: 5 - Production/Stable
Classifier: Framework :: Pytest
Classifier: Intended Audience :: Developers
Classifier: License :: OSI Approved :: MIT License
Classifier: Operating System :: OS Independent
Classifier: Programming Language :: Python
Classifier: Programming Language :: Python :: 3
Classifier: Programming Language :: Python :: 3.10
Classifier: Programming Language :: Python :: 3.7
Classifier: Programming Language :: Python :: 3.8
Classifier: Programming Language :: Python :: 3.9
Classifier: Topic :: Software Development :: Testing
Requires-Dist: importlib_metadata (>=4.5.0,<5.0.0); python_version < "3.8"
Requires-Dist: mock-generator (>=2.4,<3.0)
Project-URL: Repository, https://github.com/pksol/pytest-mock-generator
